CHANGELOG.md
CONTRIBUTING.md
INFO.md
MANIFEST.in
README.md
setup.cfg
setup.py
hotot/__init__.py
hotot/api.py
hotot/async_client.py
hotot/client.py
hotot.egg-info/PKG-INFO
hotot.egg-info/SOURCES.txt
hotot.egg-info/dependency_links.txt
hotot.egg-info/requires.txt
hotot.egg-info/top_level.txt