Metadata-Version: 2.1
Name: hotot
Version: 0.5.2
Summary: RabbitMQ/Pika Python client
Home-page: https://gitlab.lancey.fr/nuage/hotot
Author: Lancey Energy Storage
License: UNKNOWN
Platform: UNKNOWN
Classifier: Programming Language :: Python :: 3
Classifier: Operating System :: OS Independent
Classifier: Development Status :: 4 - Beta
Classifier: License :: Public Domain
